MANIFEST.in
README.txt
setup.py
bellatrix/__init__.py
bellatrix/bewitch_ami.py
bellatrix/burn_instance.py
bellatrix/connect.py
bellatrix/copy2s3.py
bellatrix/list.py
bellatrix/provision.py
bellatrix/set_permissions.py
bellatrix/set_security.py
bellatrix/start_instance.py
bellatrix/stop.py
bellatrix.egg-info/PKG-INFO
bellatrix.egg-info/SOURCES.txt
bellatrix.egg-info/dependency_links.txt
bellatrix.egg-info/requires.txt
bellatrix.egg-info/top_level.txt
bellatrix/lib/__init__.py
bellatrix/lib/bellatrix_util.py
bellatrix/lib/cmds.py
bellatrix/lib/ec2_lib.py
bellatrix/lib/util.py
bin/bellatrix
bin/bellatrix.bat