Metadata-Version: 1.0
Name: bellatrix
Version: 1.1.10
Summary: Bellatrix is a set of (magic) tools to automate the management of Amazon EC2 services.
Home-page: https://bitbucket.org/deccico/bellatrix
Author: Adrian Deccico
Author-email: deccico@gmail.com
License: Apache License 2.0
Keywords: ec2,ami,configuration,management,puppet,boto,aws,devops,sysadmin
Platform: Posix; MacOS X; Windows
Classifier: Development Status :: 5 - Production/Stable
Classifier: Environment :: Console
Classifier: Intended Audience :: Developers
Classifier: Intended Audience :: Information Technology
Classifier: Intended Audience :: System Administrators
Classifier: License :: OSI Approved :: Apache Software License
Classifier: Operating System :: OS Independent
Classifier: Programming Language :: Python
Classifier: Topic :: Internet
Classifier: Topic :: System :: Software Distribution
Classifier: Topic :: System :: Systems Administration
Classifier: Topic :: Software Development :: Libraries :: Python Modules
Classifier: Topic :: Utilities
